photo_metadata/__init__.py
photo_metadata/exiftool_japanese_tag.json
photo_metadata/photo_metadata.py
photo_metadata-0.3.0.dist-info/licenses/LICENSE.txt
photo_metadata-0.3.0.dist-info/METADATA
photo_metadata-0.3.0.dist-info/WHEEL
photo_metadata-0.3.0.dist-info/top_level.txt
photo_metadata-0.3.0.dist-info/RECORD
