Metadata-Version: 2.4
Name: photo-metadata
Version: 0.3.0
Summary: Python library to extract, read, modify, and write photo and video metadata (EXIF, IPTC, XMP) using ExifTool. Supports JPEG, RAW, and video files.
Home-page: https://github.com/kingyo1205/photo-metadata
Author: ひろ
Author-email: hirokingyo.sub@gmail.com
License: MIT
Project-URL: Documentation, https://github.com/kingyo1205/photo-metadata#readme
Project-URL: Source, https://github.com/kingyo1205/photo-metadata
Project-URL: Tracker, https://github.com/kingyo1205/photo-metadata/issues
Keywords: photo,image,metadata,exif,exiftool,iptc,xmp,video,camera,photography,raw,jpeg,picture,python,library,read,write,edit
Classifier: Development Status :: 5 - Production/Stable
Classifier: Intended Audience :: Developers
Classifier: Intended Audience :: End Users/Desktop
Classifier: License :: OSI Approved :: MIT License
Classifier: Programming Language :: Python :: 3
Classifier: Programming Language :: Python :: 3.10
Classifier: Programming Language :: Python :: 3.11
Classifier: Programming Language :: Python :: 3.12
Classifier: Programming Language :: Python :: 3.13
Classifier: Programming Language :: Python :: 3.14
Classifier: Operating System :: Microsoft :: Windows
Classifier: Operating System :: POSIX :: Linux
Classifier: Topic :: Multimedia :: Graphics :: Capture
Classifier: Topic :: Multimedia :: Graphics :: Graphics Conversion
Classifier: Topic :: Software Development :: Libraries :: Python Modules
Classifier: Topic :: Utilities
Requires-Python: >=3.10
License-File: LICENSE.txt
Requires-Dist: tqdm
Requires-Dist: charset-normalizer
Dynamic: author
Dynamic: author-email
Dynamic: classifier
Dynamic: description
Dynamic: description-content-type
Dynamic: home-page
Dynamic: keywords
Dynamic: license
Dynamic: license-file
Dynamic: project-url
Dynamic: requires-dist
Dynamic: requires-python
Dynamic: summary
